odoo/addons/cms_form/README.rst
odoo/addons/cms_form/__init__.py
odoo/addons/cms_form/__manifest__.py
odoo/addons/cms_form/exceptions.py
odoo/addons/cms_form/marshallers.py
odoo/addons/cms_form/utils.py
odoo/addons/cms_form/controllers/__init__.py
odoo/addons/cms_form/controllers/main.py
odoo/addons/cms_form/doc/Makefile
odoo/addons/cms_form/doc/source/advanced.rst
odoo/addons/cms_form/doc/source/basics.rst
odoo/addons/cms_form/doc/source/conf.py
odoo/addons/cms_form/doc/source/index.rst
odoo/addons/cms_form/doc/source/wizard.rst
odoo/addons/cms_form/doc/source/_static/images/cms_form_example_create_partner.png
odoo/addons/cms_form/doc/source/_static/images/cms_form_example_edit_partner.png
odoo/addons/cms_form/doc/source/_static/images/cms_form_example_fieldsets.png
odoo/addons/cms_form/doc/source/_static/images/cms_form_example_search.png
odoo/addons/cms_form/doc/source/_static/images/cms_form_example_tabbed.png
odoo/addons/cms_form/i18n/ca.po
odoo/addons/cms_form/i18n/cms_form.pot
odoo/addons/cms_form/i18n/de.po
odoo/addons/cms_form/i18n/es.po
odoo/addons/cms_form/i18n/fr.po
odoo/addons/cms_form/i18n/it.po
odoo/addons/cms_form/models/__init__.py
odoo/addons/cms_form/models/cms_form.py
odoo/addons/cms_form/models/cms_form_mixin.py
odoo/addons/cms_form/models/cms_form_wizard.py
odoo/addons/cms_form/models/cms_search_form.py
odoo/addons/cms_form/models/fields.py
odoo/addons/cms_form/models/widgets/__init__.py
odoo/addons/cms_form/models/widgets/widget_binary.py
odoo/addons/cms_form/models/widgets/widget_boolean.py
odoo/addons/cms_form/models/widgets/widget_date.py
odoo/addons/cms_form/models/widgets/widget_hidden.py
odoo/addons/cms_form/models/widgets/widget_many2one.py
odoo/addons/cms_form/models/widgets/widget_mixin.py
odoo/addons/cms_form/models/widgets/widget_numeric.py
odoo/addons/cms_form/models/widgets/widget_rel_mixin.py
odoo/addons/cms_form/models/widgets/widget_selection.py
odoo/addons/cms_form/models/widgets/widget_text.py
odoo_addon_cms_form-16.0.1.3.0.2.dist-info/METADATA
odoo_addon_cms_form-16.0.1.3.0.2.dist-info/WHEEL
odoo_addon_cms_form-16.0.1.3.0.2.dist-info/top_level.txt
odoo_addon_cms_form-16.0.1.3.0.2.dist-info/RECORD
