Metadata-Version: 2.1
Name: odoo-addon-cms_form
Version: 16.0.1.3.0.2
Summary: Basic content type form
Home-page: https://github.com/OCA/website-cms
Author: Camptocamp, Odoo Community Association (OCA)
Author-email: support@odoo-community.org
License: LGPL-3
Classifier: Programming Language :: Python
Classifier: Framework :: Odoo
Classifier: Framework :: Odoo :: 16.0
Classifier: License :: OSI Approved :: GNU Lesser General Public License v3 (LGPLv3)
Requires-Python: >=3.10
Requires-Dist: odoo-addon-cms-info<16.1dev,>=16.0dev
Requires-Dist: odoo-addon-cms-status-message<16.1dev,>=16.0dev
Requires-Dist: odoo<16.1dev,>=16.0a
